<?xml version="1.0" encoding="utf-8" ?>
<dwsync>
<file name="glyphicons-halflings-regular.eot" server="mforsberg.dk/public_html/" local="131256908318065883" remote="131267204400000000" Dst="1" />
<file name="glyphicons-halflings-regular.ttf" server="mforsberg.dk/public_html/" local="131256908318155971" remote="131267204400000000" Dst="1" />
<file name="glyphicons-halflings-regular.svg" server="mforsberg.dk/public_html/" local="131256908318115929" remote="131267205000000000" Dst="1" />
<file name="glyphicons-halflings-regular.woff" server="mforsberg.dk/public_html/" local="131256908318186001" remote="131267204400000000" Dst="1" />
<file name="glyphicons-halflings-regular.woff2" server="mforsberg.dk/public_html/" local="131256908318206020" remote="131267204400000000" Dst="1" />
<file name="glyphicons-halflings-regular.eot" server="www.mforsberg.dk/public_html/" local="130771760320000000" remote="131267239200000000" Dst="1" />
<file name="glyphicons-halflings-regular.ttf" server="www.mforsberg.dk/public_html/" local="130771760320000000" remote="131267239200000000" Dst="1" />
<file name="glyphicons-halflings-regular.woff" server="www.mforsberg.dk/public_html/" local="130771760320000000" remote="131267239200000000" Dst="1" />
<file name="glyphicons-halflings-regular.svg" server="www.mforsberg.dk/public_html/" local="130771760320000000" remote="131267239200000000" Dst="1" />
<file name="glyphicons-halflings-regular.woff2" server="www.mforsberg.dk/public_html/" local="130771760320000000" remote="131267239200000000" Dst="1" />
</dwsync>